Metadata-Version: 1.1
Name: blather
Version: 1.0.1
Summary: Train and use generative language models with only three lines of code.
Home-page: https://github.com/bigthonk/blather
Author: Dan Carroll
Author-email: dcarroll314@gmail.com
License: Apache 2.0
Keywords: GPT3,natural language,huggingface,pytorch
Platform: UNKNOWN
Classifier: License :: OSI Approved :: Apache Software License
Classifier: Programming Language :: Python :: 3
Classifier: Programming Language :: Python :: 3.6
